bingart/__init__.py
bingart/bingart.py
bingart-1.5.0.dist-info/licenses/LICENSE
bingart-1.5.0.dist-info/METADATA
bingart-1.5.0.dist-info/WHEEL
bingart-1.5.0.dist-info/top_level.txt
bingart-1.5.0.dist-info/RECORD
